objectsync/__init__.py
objectsync/count.py
objectsync/hierarchy_utils.py
objectsync/history.py
objectsync/server.py
objectsync/sobject.py
objectsync/topic.py
objectsync/utils.py
objectsync-0.10.0.dist-info/METADATA
objectsync-0.10.0.dist-info/WHEEL
objectsync-0.10.0.dist-info/RECORD
