Metadata-Version: 2.1
Name: objectsync
Version: 0.10.0
Summary: 
Author: eri24816
Author-email: a931eric@gmail.com
Maintainer: eri24816
Maintainer-email: a931eric@gmail.com
Requires-Python: >=3.11,<4.0
Classifier: Programming Language :: Python :: 3
Classifier: Programming Language :: Python :: 3.11
Requires-Dist: topicsync (>=0.13.0)
